{
  "interaction_id": 84,
  "generated_at": "2025-11-11T11:55:10.421787",
  "data": {
    "chains": [
      "A",
      "B"
    ],
    "chain_lengths": {
      "A": 665,
      "B": 199
    },
    "contacts": [
      {
        "chain1": "A",
        "resi1": 483,
        "aa1": "E",
        "chain2": "B",
        "resi2": 86,
        "aa2": "A",
        "pae": 8.4,
        "distance": 4.89,
        "confidence": "low",
        "color": "#ff4500"
      },
      {
        "chain1": "A",
        "resi1": 483,
        "aa1": "E",
        "chain2": "B",
        "resi2": 87,
        "aa2": "F",
        "pae": 9.0,
        "distance": 4.79,
        "confidence": "low",
        "color": "#ff4500"
      },
      {
        "chain1": "A",
        "resi1": 484,
        "aa1": "P",
        "chain2": "B",
        "resi2": 118,
        "aa2": "E",
        "pae": 7.2,
        "distance": 4.43,
        "confidence": "medium",
        "color": "#ffff00"
      },
      {
        "chain1": "A",
        "resi1": 486,
        "aa1": "V",
        "chain2": "B",
        "resi2": 87,
        "aa2": "F",
        "pae": 7.4,
        "distance": 4.29,
        "confidence": "medium",
        "color": "#ffff00"
      },
      {
        "chain1": "A",
        "resi1": 487,
        "aa1": "K",
        "chain2": "B",
        "resi2": 86,
        "aa2": "A",
        "pae": 7.6,
        "distance": 3.74,
        "confidence": "medium",
        "color": "#ffff00"
      },
      {
        "chain1": "A",
        "resi1": 487,
        "aa1": "K",
        "chain2": "B",
        "resi2": 87,
        "aa2": "F",
        "pae": 7.0,
        "distance": 4.38,
        "confidence": "medium",
        "color": "#ffff00"
      },
      {
        "chain1": "A",
        "resi1": 487,
        "aa1": "K",
        "chain2": "B",
        "resi2": 90,
        "aa2": "M",
        "pae": 7.1,
        "distance": 3.3,
        "confidence": "medium",
        "color": "#ffff00"
      },
      {
        "chain1": "A",
        "resi1": 487,
        "aa1": "K",
        "chain2": "B",
        "resi2": 114,
        "aa2": "V",
        "pae": 5.6,
        "distance": 3.62,
        "confidence": "medium",
        "color": "#ffff00"
      },
      {
        "chain1": "A",
        "resi1": 487,
        "aa1": "K",
        "chain2": "B",
        "resi2": 117,
        "aa2": "W",
        "pae": 7.7,
        "distance": 3.46,
        "confidence": "medium",
        "color": "#ffff00"
      },
      {
        "chain1": "A",
        "resi1": 487,
        "aa1": "K",
        "chain2": "B",
        "resi2": 118,
        "aa2": "E",
        "pae": 7.0,
        "distance": 4.34,
        "confidence": "medium",
        "color": "#ffff00"
      },
      {
        "chain1": "A",
        "resi1": 488,
        "aa1": "K",
        "chain2": "B",
        "resi2": 112,
        "aa2": "Q",
        "pae": 6.8,
        "distance": 4.13,
        "confidence": "medium",
        "color": "#ffff00"
      },
      {
        "chain1": "A",
        "resi1": 488,
        "aa1": "K",
        "chain2": "B",
        "resi2": 114,
        "aa2": "V",
        "pae": 6.5,
        "distance": 3.86,
        "confidence": "medium",
        "color": "#ffff00"
      },
      {
        "chain1": "A",
        "resi1": 490,
        "aa1": "Y",
        "chain2": "B",
        "resi2": 87,
        "aa2": "F",
        "pae": 6.9,
        "distance": 3.28,
        "confidence": "medium",
        "color": "#ffff00"
      },
      {
        "chain1": "A",
        "resi1": 490,
        "aa1": "Y",
        "chain2": "B",
        "resi2": 90,
        "aa2": "M",
        "pae": 6.7,
        "distance": 3.43,
        "confidence": "medium",
        "color": "#ffff00"
      },
      {
        "chain1": "A",
        "resi1": 490,
        "aa1": "Y",
        "chain2": "B",
        "resi2": 91,
        "aa2": "E",
        "pae": 6.7,
        "distance": 2.94,
        "confidence": "medium",
        "color": "#ffff00"
      },
      {
        "chain1": "A",
        "resi1": 490,
        "aa1": "Y",
        "chain2": "B",
        "resi2": 94,
        "aa2": "S",
        "pae": 6.6,
        "distance": 3.98,
        "confidence": "medium",
        "color": "#ffff00"
      },
      {
        "chain1": "A",
        "resi1": 490,
        "aa1": "Y",
        "chain2": "B",
        "resi2": 113,
        "aa2": "T",
        "pae": 5.8,
        "distance": 4.03,
        "confidence": "medium",
        "color": "#ffff00"
      },
      {
        "chain1": "A",
        "resi1": 491,
        "aa1": "D",
        "chain2": "B",
        "resi2": 94,
        "aa2": "S",
        "pae": 8.7,
        "distance": 3.83,
        "confidence": "low",
        "color": "#ff4500"
      },
      {
        "chain1": "A",
        "resi1": 491,
        "aa1": "D",
        "chain2": "B",
        "resi2": 97,
        "aa2": "L",
        "pae": 7.8,
        "distance": 3.88,
        "confidence": "medium",
        "color": "#ffff00"
      },
      {
        "chain1": "A",
        "resi1": 491,
        "aa1": "D",
        "chain2": "B",
        "resi2": 111,
        "aa2": "F",
        "pae": 7.1,
        "distance": 4.98,
        "confidence": "medium",
        "color": "#ffff00"
      },
      {
        "chain1": "A",
        "resi1": 491,
        "aa1": "D",
        "chain2": "B",
        "resi2": 112,
        "aa2": "Q",
        "pae": 6.4,
        "distance": 3.43,
        "confidence": "medium",
        "color": "#ffff00"
      },
      {
        "chain1": "A",
        "resi1": 491,
        "aa1": "D",
        "chain2": "B",
        "resi2": 113,
        "aa2": "T",
        "pae": 5.8,
        "distance": 2.5,
        "confidence": "medium",
        "color": "#ffff00"
      },
      {
        "chain1": "A",
        "resi1": 491,
        "aa1": "D",
        "chain2": "B",
        "resi2": 114,
        "aa2": "V",
        "pae": 7.7,
        "distance": 4.66,
        "confidence": "medium",
        "color": "#ffff00"
      },
      {
        "chain1": "A",
        "resi1": 504,
        "aa1": "L",
        "chain2": "B",
        "resi2": 87,
        "aa2": "F",
        "pae": 7.9,
        "distance": 4.56,
        "confidence": "medium",
        "color": "#ffff00"
      },
      {
        "chain1": "A",
        "resi1": 508,
        "aa1": "Y",
        "chain2": "B",
        "resi2": 87,
        "aa2": "F",
        "pae": 9.1,
        "distance": 3.43,
        "confidence": "low",
        "color": "#ff4500"
      },
      {
        "chain1": "A",
        "resi1": 515,
        "aa1": "E",
        "chain2": "B",
        "resi2": 85,
        "aa2": "M",
        "pae": 8.5,
        "distance": 3.51,
        "confidence": "low",
        "color": "#ff4500"
      },
      {
        "chain1": "A",
        "resi1": 515,
        "aa1": "E",
        "chain2": "B",
        "resi2": 88,
        "aa2": "K",
        "pae": 9.3,
        "distance": 4.71,
        "confidence": "low",
        "color": "#ff4500"
      },
      {
        "chain1": "A",
        "resi1": 516,
        "aa1": "E",
        "chain2": "B",
        "resi2": 85,
        "aa2": "M",
        "pae": 8.9,
        "distance": 3.77,
        "confidence": "low",
        "color": "#ff4500"
      },
      {
        "chain1": "A",
        "resi1": 516,
        "aa1": "E",
        "chain2": "B",
        "resi2": 87,
        "aa2": "F",
        "pae": 7.8,
        "distance": 3.88,
        "confidence": "medium",
        "color": "#ffff00"
      },
      {
        "chain1": "A",
        "resi1": 519,
        "aa1": "E",
        "chain2": "B",
        "resi2": 85,
        "aa2": "M",
        "pae": 8.6,
        "distance": 4.22,
        "confidence": "low",
        "color": "#ff4500"
      },
      {
        "chain1": "A",
        "resi1": 519,
        "aa1": "E",
        "chain2": "B",
        "resi2": 87,
        "aa2": "F",
        "pae": 9.2,
        "distance": 4.05,
        "confidence": "low",
        "color": "#ff4500"
      },
      {
        "chain1": "A",
        "resi1": 519,
        "aa1": "E",
        "chain2": "B",
        "resi2": 88,
        "aa2": "K",
        "pae": 7.4,
        "distance": 3.06,
        "confidence": "medium",
        "color": "#ffff00"
      },
      {
        "chain1": "A",
        "resi1": 520,
        "aa1": "L",
        "chain2": "B",
        "resi2": 87,
        "aa2": "F",
        "pae": 7.2,
        "distance": 4.24,
        "confidence": "medium",
        "color": "#ffff00"
      },
      {
        "chain1": "A",
        "resi1": 523,
        "aa1": "K",
        "chain2": "B",
        "resi2": 91,
        "aa2": "E",
        "pae": 6.6,
        "distance": 2.75,
        "confidence": "medium",
        "color": "#ffff00"
      },
      {
        "chain1": "A",
        "resi1": 523,
        "aa1": "K",
        "chain2": "B",
        "resi2": 94,
        "aa2": "S",
        "pae": 8.0,
        "distance": 3.31,
        "confidence": "low",
        "color": "#ff4500"
      },
      {
        "chain1": "A",
        "resi1": 526,
        "aa1": "K",
        "chain2": "B",
        "resi2": 91,
        "aa2": "E",
        "pae": 8.8,
        "distance": 2.55,
        "confidence": "low",
        "color": "#ff4500"
      },
      {
        "chain1": "A",
        "resi1": 526,
        "aa1": "K",
        "chain2": "B",
        "resi2": 95,
        "aa2": "Q",
        "pae": 9.2,
        "distance": 4.14,
        "confidence": "low",
        "color": "#ff4500"
      }
    ],
    "summary": {
      "total_contacts": 37,
      "very_high_count": 0,
      "high_count": 0,
      "medium_count": 25,
      "low_count": 12
    },
    "spatial_validation_enabled": true
  }
}